[
  { "g": "Apakah kucing mengalami bulu rontok ?"},
  { "g": "Apakah kucing mengalami kulit berkerak?"},
  { "g": "Apakah kucing mengalami jamur di bagian kulit?"},
  { "g": "Apakah kucing mengalami telinga berkerak ?"},
  { "g": "Apakah kucing selalu menggaruk dibagian telinga?"},
  { "g": "Apakah kucing mengalami kemerahan dibagian kulit?"},
  { "g": "Apakah kucing mengalami bersin terus menerus?"},
  { "g": "Apakah kucing mengalami gangguan pencernaan?"},
  { "g": "Apakah kucing terlihat lemah dan lesu?"},
  { "g": "Apakah kucing mengalami munculnya kutu di badan?"},
  { "g": "Apakah kucing mengalami peradangan akibat gigitan kutu?"},
  { "g": "Apakah terdapat benjolan di kulit pada kucing?"},
  { "g": "Apakah terdapat luka pada bibir kucing?"},
  { "g": "Apakah kucing mengalami demam?"},
  { "g": "Apakah terdapat lapisan kulit di bulu pada kulit kucing?"},
  { "g": "Apakah terdapat infeksi kulit dan pembengkakan pada kulit kucing?"},
  { "g": "Apakah ekor kucing mengeluarkan kelenjar minyak?"}

]